helldivers2_api/__init__.py
helldivers2_api/api_client.py
helldivers2_api/api_version.py
helldivers2_api/campaign.py
helldivers2_api/endpoint_map.py
helldivers2_api/faction.py
helldivers2_api/global_event.py
helldivers2_api/joint_operation.py
helldivers2_api/mapping_strategy.py
helldivers2_api/news.py
helldivers2_api/planet.py
helldivers2_api/planet_attack.py
helldivers2_api/planet_event.py
helldivers2_api/planet_info_table.py
helldivers2_api/planet_status.py
helldivers2_api/sector.py
helldivers2_api/war_status.py
helldivers_2_api-0.0.3.dist-info/LICENCE.md
helldivers_2_api-0.0.3.dist-info/METADATA
helldivers_2_api-0.0.3.dist-info/WHEEL
helldivers_2_api-0.0.3.dist-info/top_level.txt
helldivers_2_api-0.0.3.dist-info/RECORD
