Metadata-Version: 2.1
Name: helldivers-2-api
Version: 0.0.3
Summary: A Python abstraction layer for the Helldivers 2 API
Author-email: David Rodenkirchen <davidr.develop@gmail.com>
Project-URL: Repository, https://git.jdrodenkirchen.de/drodenkirchen/helldivers-2-python-api
Project-URL: Discord, https://discord.gg/kKuxparXWT
Classifier: Programming Language :: Python :: 3
Classifier: License :: Other/Proprietary License
Classifier: Operating System :: OS Independent
Classifier: Development Status :: 5 - Production/Stable
Classifier: Topic :: Games/Entertainment
Classifier: Topic :: System :: Networking
Classifier: Typing :: Typed
Requires-Python: >=3.11
License-File: LICENCE.md
Requires-Dist: requests >=2.31.0
